composable_mapping/__init__.py
composable_mapping/affine_mapping.py
composable_mapping/constant.py
composable_mapping/derivative.py
composable_mapping/factory.py
composable_mapping/interface.py
composable_mapping/mask.py
composable_mapping/py.typed
composable_mapping/tensor_like.py
composable_mapping/util.py
composable_mapping/visualization.py
composable_mapping/affine_transformation/__init__.py
composable_mapping/affine_transformation/affine_transformation.py
composable_mapping/affine_transformation/diagonal_matrix.py
composable_mapping/affine_transformation/matrix.py
composable_mapping/composable_mapping/__init__.py
composable_mapping/composable_mapping/composable_mapping.py
composable_mapping/composable_mapping/interface.py
composable_mapping/composable_mapping/util.py
composable_mapping/coordinate_system/__init__.py
composable_mapping/coordinate_system/coordinate_system.py
composable_mapping/coordinate_system/reformatting_reference.py
composable_mapping/coordinate_system/reformatting_spatial_shape.py
composable_mapping/mappable_tensor/__init__.py
composable_mapping/mappable_tensor/grid.py
composable_mapping/mappable_tensor/mappable_tensor.py
composable_mapping/mappable_tensor/util.py
composable_mapping/sampler/__init__.py
composable_mapping/sampler/b_spline.py
composable_mapping/sampler/convolution_sampling.py
composable_mapping/sampler/default.py
composable_mapping/sampler/interface.py
composable_mapping/sampler/interpolate.py
composable_mapping/sampler/interpolator.py
composable_mapping/sampler/inverse.py
composable_mapping/sampler/sampling_cache.py
composable_mapping/sampler/scaling_and_squaring.py
composable_mapping/sampler/separable_sampler.py
composable_mapping/sampler/_second_order_differentiable_grid_sample/__init__.py
composable_mapping/sampler/_second_order_differentiable_grid_sample/cuda_gridsample.py
composable_mapping/sampler/_second_order_differentiable_grid_sample/grid_sample.py
composable_mapping-0.1.4.dist-info/LICENSE
composable_mapping-0.1.4.dist-info/METADATA
composable_mapping-0.1.4.dist-info/WHEEL
composable_mapping-0.1.4.dist-info/top_level.txt
composable_mapping-0.1.4.dist-info/RECORD
