Metadata-Version: 2.2
Name: composable-mapping
Version: 0.1.4
Summary: Composable mapping is a PyTorch utility library for handling geometric deformations
Author: Joel Honkamaa
License: MIT License
Project-URL: Homepage, https://github.com/honkamj/composable-mapping
Keywords: deep learning,neural networks,image registration,deformation,coordinate mapping,pytorch
Classifier: Programming Language :: Python :: 3
Classifier: License :: OSI Approved :: MIT License
Classifier: Operating System :: OS Independent
Requires-Python: >=3.8
License-File: LICENSE
Requires-Dist: torch>=2.0
Requires-Dist: deformation_inversion_layer>=1.1.2
Requires-Dist: nibabel
Requires-Dist: matplotlib
